<?xml version="1.0" encoding="utf-8" ?>
<dwsync>
<file name="index.html" server="sv3.html.xdomain.ne.jp" local="132152295970094937" remote="132152310600000000" Dst="0" />
<file name="large_catalog_01.html" server="sv3.html.xdomain.ne.jp" local="132152291072575871" remote="132152311200000000" Dst="0" />
<file name="large_catalog_03.html" server="sv3.html.xdomain.ne.jp" local="132152291577014883" remote="132152311200000000" Dst="0" />
<file name="large_catalog_02.html" server="sv3.html.xdomain.ne.jp" local="132152291397425762" remote="132152311200000000" Dst="0" />
<file name="large_flyer_01.html" server="sv3.html.xdomain.ne.jp" local="132152291741590495" remote="132152311200000000" Dst="0" />
<file name="large_flyer_03.html" server="sv3.html.xdomain.ne.jp" local="132152291971164122" remote="132152311200000000" Dst="0" />
<file name="large_flyer_02.html" server="sv3.html.xdomain.ne.jp" local="132152291864162591" remote="132152311200000000" Dst="0" />
<file name="large_flyer_04.html" server="sv3.html.xdomain.ne.jp" local="132152292079530408" remote="132152311200000000" Dst="0" />
<file name="large_flyer_06.html" server="sv3.html.xdomain.ne.jp" local="132152292275988561" remote="132152311800000000" Dst="0" />
<file name="large_flyer_05.html" server="sv3.html.xdomain.ne.jp" local="132152292172268847" remote="132152311800000000" Dst="0" />
<file name="large_magazin_01.html" server="sv3.html.xdomain.ne.jp" local="132152292553669409" remote="132152311800000000" Dst="0" />
<file name="large_magazin_02.html" server="sv3.html.xdomain.ne.jp" local="132152292735667916" remote="132152311800000000" Dst="0" />
<file name="large_magazin_03.html" server="sv3.html.xdomain.ne.jp" local="132152292829391366" remote="132152311800000000" Dst="0" />
<file name="large_other_01.html" server="sv3.html.xdomain.ne.jp" local="132152292964087234" remote="132152311800000000" Dst="0" />
<file name="large_other_02.html" server="sv3.html.xdomain.ne.jp" local="132152293069224120" remote="132152312400000000" Dst="0" />
<file name="large_other_03.html" server="sv3.html.xdomain.ne.jp" local="132152293169766237" remote="132152312400000000" Dst="0" />
<file name="large_poster_02.html" server="sv3.html.xdomain.ne.jp" local="132152293391868371" remote="132152312400000000" Dst="0" />
<file name="large_poster_03.html" server="sv3.html.xdomain.ne.jp" local="132152293499971995" remote="132152312400000000" Dst="0" />
<file name="large_poster_01.html" server="sv3.html.xdomain.ne.jp" local="132152293278904710" remote="132152312400000000" Dst="0" />
<file name="large_poster_04.html" server="sv3.html.xdomain.ne.jp" local="132152293665819004" remote="132152312400000000" Dst="0" />
<file name="large_poster_05.html" server="sv3.html.xdomain.ne.jp" local="132149954260000000" remote="132150798600000000" Dst="0" />
<file name="large_poster_06.html" server="sv3.html.xdomain.ne.jp" local="132152293781761095" remote="132152313000000000" Dst="0" />
<file name="large_school_01.html" server="sv3.html.xdomain.ne.jp" local="132152293897527685" remote="132152313000000000" Dst="0" />
<file name="large_school_02.html" server="sv3.html.xdomain.ne.jp" local="132152293997935813" remote="132152313000000000" Dst="0" />
<file name="large_school_03.html" server="sv3.html.xdomain.ne.jp" local="132152294126395770" remote="132152313000000000" Dst="0" />
<file name="large_school_04.html" server="sv3.html.xdomain.ne.jp" local="132152294252195338" remote="132152313000000000" Dst="0" />
<file name="large_school_05.html" server="sv3.html.xdomain.ne.jp" local="132152294362555915" remote="132152313000000000" Dst="0" />
<file name="works.html" server="sv3.html.xdomain.ne.jp" local="132152310417502231" remote="132152313000000000" Dst="0" />
</dwsync>